{"fire": [{"X": 5, "Y": 5, "Z": 86, "Datum": "19.684294"}, {"X": 5, "Y": 6, "Z": 86, "Datum": "17.650436"}, {"X": 5, "Y": 7, "Z": 86, "Datum": "16.209324"}, {"X": 5, "Y": 7, "Z": 87, "Datum": "16.131006"}, {"X": 5, "Y": 9, "Z": 89, "Datum": "15.4453"}, {"X": 6, "Y": 9, "Z": 75, "Datum": "21.121141"}, {"X": 6, "Y": 9, "Z": 76, "Datum": "34.67939"}, {"X": 6, "Y": 9, "Z": 77, "Datum": "24.431093"}, {"X": 6, "Y": 10, "Z": 75, "Datum": "24.15009"}, {"X": 6, "Y": 10, "Z": 76, "Datum": "34.877567"}, {"X": 6, "Y": 10, "Z": 77, "Datum": "30.204258"}, {"X": 6, "Y": 11, "Z": 74, "Datum": "19.408298"}, {"X": 6, "Y": 11, "Z": 75, "Datum": "29.293394"}, {"X": 6, "Y": 11, "Z": 76, "Datum": "44.698956"}, {"X": 6, "Y": 11, "Z": 77, "Datum": "29.365786"}, {"X": 6, "Y": 12, "Z": 74, "Datum": "19.408298"}, {"X": 6, "Y": 12, "Z": 75, "Datum": "30.350573"}, {"X": 6, "Y": 12, "Z": 76, "Datum": "54.322166"}, {"X": 6, "Y": 12, "Z": 77, "Datum": "34.55331"}, {"X": 7, "Y": 3, "Z": 78, "Datum": "16.187473"}, {"X": 7, "Y": 7, "Z": 76, "Datum": "18.023464"}, {"X": 7, "Y": 8, "Z": 72, "Datum": "17.955631"}, {"X": 7, "Y": 8, "Z": 73, "Datum": "33.39664"}, {"X": 7, "Y": 8, "Z": 74, "Datum": "32.230984"}, {"X": 7, "Y": 8, "Z": 75, "Datum": "30.727041"}, {"X": 7, "Y": 8, "Z": 76, "Datum": "57.85114"}, {"X": 7, "Y": 8, "Z": 77, "Datum": "26.731077"}, {"X": 7, "Y": 9, "Z": 73, "Datum": "27.069897"}, {"X": 7, "Y": 9, "Z": 74, "Datum": "36.613815"}, {"X": 7, "Y": 9, "Z": 75, "Datum": "36.12594"}, {"X": 7, "Y": 9, "Z": 76, "Datum": "49.461895"}, {"X": 7, "Y": 9, "Z": 77, "Datum": "30.86303"}, {"X": 7, "Y": 10, "Z": 75, "Datum": "18.125145"}, {"X": 7, "Y": 10, "Z": 76, "Datum": "26.656796"}, {"X": 7, "Y": 10, "Z": 77, "Datum": "20.674376"}, {"X": 7, "Y": 11, "Z": 75, "Datum": "18.19197"}, {"X": 7, "Y": 11, "Z": 76, "Datum": "25.551756"}, {"X": 7, "Y": 11, "Z": 77, "Datum": "15.707968"}, {"X": 7, "Y": 12, "Z": 75, "Datum": "20.14716"}, {"X": 7, "Y": 12, "Z": 76, "Datum": "27.953184"}, {"X": 7, "Y": 12, "Z": 77, "Datum": "17.224522"}, {"X": 7, "Y": 13, "Z": 75, "Datum": "32.80276"}, {"X": 7, "Y": 13, "Z": 76, "Datum": "60.500374"}, {"X": 7, "Y": 13, "Z": 77, "Datum": "66.21885"}, {"X": 7, "Y": 13, "Z": 78, "Datum": "60.847656"}, {"X": 7, "Y": 13, "Z": 79, "Datum": "55.227962"}, {"X": 7, "Y": 13, "Z": 80, "Datum": "57.068497"}, {"X": 7, "Y": 13, "Z": 81, "Datum": "71.256134"}, {"X": 7, "Y": 13, "Z": 93, "Datum": "18.47139"}, {"X": 7, "Y": 14, "Z": 74, "Datum": "18.35987"}, {"X": 7, "Y": 14, "Z": 75, "Datum": "49.497635"}, {"X": 7, "Y": 14, "Z": 76, "Datum": "98.72995"}, {"X": 7, "Y": 14, "Z": 77, "Datum": "117.019745"}, {"X": 7, "Y": 14, "Z": 78, "Datum": "119.69061"}, {"X": 7, "Y": 14, "Z": 79, "Datum": "104.71602"}, {"X": 7, "Y": 14, "Z": 80, "Datum": "103.56178"}, {"X": 7, "Y": 14, "Z": 81, "Datum": "130.89375"}, {"X": 7, "Y": 14, "Z": 92, "Datum": "16.288387"}, {"X": 7, "Y": 14, "Z": 93, "Datum": "16.691002"}, {"X": 7, "Y": 15, "Z": 93, "Datum": "15.648115"}, {"X": 8, "Y": 2, "Z": 74, "Datum": "18.070677"}, {"X": 8, "Y": 2, "Z": 75, "Datum": "15.146661"}, {"X": 8, "Y": 5, "Z": 71, "Datum": "31.478039"}, {"X": 8, "Y": 5, "Z": 72, "Datum": "18.778128"}, {"X": 8, "Y": 6, "Z": 71, "Datum": "27.6247"}, {"X": 8, "Y": 6, "Z": 72, "Datum": "22.171602"}, {"X": 8, "Y": 7, "Z": 71, "Datum": "32.474102"}, {"X": 8, "Y": 7, "Z": 72, "Datum": "27.434261"}, {"X": 8, "Y": 8, "Z": 70, "Datum": "15.429907"}, {"X": 8, "Y": 8, "Z": 71, "Datum": "31.23215"}, {"X": 8, "Y": 8, "Z": 72, "Datum": "25.721937"}, {"X": 8, "Y": 8, "Z": 73, "Datum": "16.301355"}, {"X": 8, "Y": 8, "Z": 75, "Datum": "15.858086"}, {"X": 8, "Y": 8, "Z": 76, "Datum": "29.726482"}, {"X": 8, "Y": 8, "Z": 77, "Datum": "20.477571"}, {"X": 8, "Y": 9, "Z": 73, "Datum": "15.899876"}, {"X": 8, "Y": 9, "Z": 74, "Datum": "19.987898"}, {"X": 8, "Y": 9, "Z": 75, "Datum": "22.318628"}, {"X": 8, "Y": 9, "Z": 76, "Datum": "31.123373"}, {"X": 8, "Y": 9, "Z": 77, "Datum": "19.123808"}, {"X": 8, "Y": 13, "Z": 75, "Datum": "19.928738"}, {"X": 8, "Y": 13, "Z": 76, "Datum": "33.369434"}, {"X": 8, "Y": 13, "Z": 77, "Datum": "35.234024"}, {"X": 8, "Y": 13, "Z": 78, "Datum": "32.34905"}, {"X": 8, "Y": 13, "Z": 79, "Datum": "30.459818"}, {"X": 8, "Y": 13, "Z": 80, "Datum": "35.800953"}, {"X": 8, "Y": 13, "Z": 81, "Datum": "40.623688"}, {"X": 8, "Y": 14, "Z": 75, "Datum": "35.32815"}, {"X": 8, "Y": 14, "Z": 76, "Datum": "80.20545"}, {"X": 8, "Y": 14, "Z": 77, "Datum": "101.298744"}, {"X": 8, "Y": 14, "Z": 78, "Datum": "91.95386"}, {"X": 8, "Y": 14, "Z": 79, "Datum": "78.58643"}, {"X": 8, "Y": 14, "Z": 80, "Datum": "90.389366"}, {"X": 8, "Y": 14, "Z": 81, "Datum": "99.0216"}, {"X": 8, "Y": 14, "Z": 82, "Datum": "29.061995"}, {"X": 8, "Y": 15, "Z": 75, "Datum": "44.11829"}, {"X": 8, "Y": 15, "Z": 76, "Datum": "130.3143"}, {"X": 8, "Y": 15, "Z": 77, "Datum": "178.94481"}, {"X": 8, "Y": 15, "Z": 78, "Datum": "148.991"}, {"X": 8, "Y": 15, "Z": 79, "Datum": "120.58857"}, {"X": 8, "Y": 15, "Z": 80, "Datum": "139.84192"}, {"X": 8, "Y": 15, "Z": 81, "Datum": "165.92332"}, {"X": 8, "Y": 17, "Z": 93, "Datum": "18.48538"}, {"X": 8, "Y": 17, "Z": 94, "Datum": "15.000559"}, {"X": 9, "Y": 2, "Z": 71, "Datum": "22.559998"}, {"X": 9, "Y": 2, "Z": 72, "Datum": "23.174171"}, {"X": 9, "Y": 3, "Z": 70, "Datum": "17.913565"}, {"X": 9, "Y": 3, "Z": 71, "Datum": "31.272072"}, {"X": 9, "Y": 4, "Z": 70, "Datum": "30.012587"}, {"X": 9, "Y": 4, "Z": 71, "Datum": "29.865906"}, {"X": 9, "Y": 5, "Z": 70, "Datum": "18.757423"}, {"X": 9, "Y": 5, "Z": 71, "Datum": "23.247925"}, {"X": 9, "Y": 6, "Z": 71, "Datum": "17.461472"}, {"X": 9, "Y": 7, "Z": 71, "Datum": "17.26389"}, {"X": 9, "Y": 8, "Z": 71, "Datum": "16.246077"}, {"X": 9, "Y": 14, "Z": 75, "Datum": "18.459265"}, {"X": 9, "Y": 14, "Z": 76, "Datum": "40.644726"}, {"X": 9, "Y": 14, "Z": 77, "Datum": "50.79561"}, {"X": 9, "Y": 14, "Z": 78, "Datum": "41.586155"}, {"X": 9, "Y": 14, "Z": 79, "Datum": "35.579983"}, {"X": 9, "Y": 14, "Z": 80, "Datum": "48.038956"}, {"X": 9, "Y": 14, "Z": 81, "Datum": "48.81671"}, {"X": 9, "Y": 14, "Z": 82, "Datum": "16.84155"}, {"X": 9, "Y": 15, "Z": 75, "Datum": "24.32968"}, {"X": 9, "Y": 15, "Z": 76, "Datum": "54.005154"}, {"X": 9, "Y": 15, "Z": 77, "Datum": "67.4409"}, {"X": 9, "Y": 15, "Z": 78, "Datum": "54.756367"}, {"X": 9, "Y": 15, "Z": 79, "Datum": "47.2564"}, {"X": 9, "Y": 15, "Z": 80, "Datum": "58.322422"}, {"X": 9, "Y": 15, "Z": 81, "Datum": "61.872192"}, {"X": 9, "Y": 15, "Z": 82, "Datum": "21.145872"}, {"X": 10, "Y": 3, "Z": 71, "Datum": "15.958161"}, {"X": 10, "Y": 4, "Z": 70, "Datum": "15.588682"}, {"X": 10, "Y": 4, "Z": 71, "Datum": "15.419782"}, {"X": 10, "Y": 15, "Z": 81, "Datum": "19.829695"}, {"X": 10, "Y": 16, "Z": 81, "Datum": "25.87175"}, {"X": 10, "Y": 16, "Z": 82, "Datum": "38.79989"}, {"X": 10, "Y": 16, "Z": 83, "Datum": "22.58357"}, {"X": 10, "Y": 17, "Z": 80, "Datum": "27.806053"}, {"X": 10, "Y": 17, "Z": 81, "Datum": "72.65102"}, {"X": 10, "Y": 17, "Z": 82, "Datum": "110.81382"}, {"X": 10, "Y": 17, "Z": 83, "Datum": "82.80669"}, {"X": 10, "Y": 17, "Z": 84, "Datum": "25.595835"}, {"X": 10, "Y": 18, "Z": 79, "Datum": "16.815151"}, {"X": 10, "Y": 18, "Z": 80, "Datum": "62.253334"}, {"X": 10, "Y": 18, "Z": 81, "Datum": "134.82385"}, {"X": 10, "Y": 18, "Z": 82, "Datum": "166.27872"}, {"X": 10, "Y": 18, "Z": 83, "Datum": "122.16931"}, {"X": 10, "Y": 18, "Z": 84, "Datum": "44.994164"}, {"X": 11, "Y": 16, "Z": 81, "Datum": "19.129288"}, {"X": 11, "Y": 16, "Z": 82, "Datum": "19.778507"}, {"X": 11, "Y": 17, "Z": 80, "Datum": "25.873707"}, {"X": 11, "Y": 17, "Z": 81, "Datum": "49.645187"}, {"X": 11, "Y": 17, "Z": 82, "Datum": "57.55078"}, {"X": 11, "Y": 17, "Z": 83, "Datum": "42.788113"}, {"X": 11, "Y": 17, "Z": 84, "Datum": "16.618185"}, {"X": 11, "Y": 18, "Z": 80, "Datum": "31.733263"}, {"X": 11, "Y": 18, "Z": 81, "Datum": "54.887314"}, {"X": 11, "Y": 18, "Z": 82, "Datum": "60.528416"}, {"X": 11, "Y": 18, "Z": 83, "Datum": "51.156162"}, {"X": 11, "Y": 18, "Z": 84, "Datum": "35.950924"}, {"X": 11, "Y": 18, "Z": 85, "Datum": "15.012607"}, {"X": 11, "Y": 19, "Z": 84, "Datum": "89.37602"}, {"X": 11, "Y": 19, "Z": 85, "Datum": "49.67542"}, {"X": 11, "Y": 20, "Z": 84, "Datum": "171.43239"}, {"X": 11, "Y": 20, "Z": 85, "Datum": "115.594246"}, {"X": 11, "Y": 20, "Z": 86, "Datum": "65.835915"}, {"X": 11, "Y": 20, "Z": 87, "Datum": "24.404795"}, {"X": 11, "Y": 21, "Z": 84, "Datum": "249.99974"}, {"X": 11, "Y": 21, "Z": 85, "Datum": "175.57487"}, {"X": 11, "Y": 21, "Z": 86, "Datum": "138.65967"}, {"X": 11, "Y": 21, "Z": 87, "Datum": "65.84081"}, {"X": 11, "Y": 22, "Z": 86, "Datum": "147.34319"}, {"X": 11, "Y": 22, "Z": 87, "Datum": "80.92117"}, {"X": 11, "Y": 23, "Z": 86, "Datum": "117.84932"}, {"X": 11, "Y": 23, "Z": 87, "Datum": "80.071884"}, {"X": 11, "Y": 23, "Z": 88, "Datum": "48.475914"}, {"X": 11, "Y": 23, "Z": 89, "Datum": "15.176601"}, {"X": 11, "Y": 24, "Z": 87, "Datum": "105.33174"}, {"X": 11, "Y": 24, "Z": 88, "Datum": "84.97917"}, {"X": 11, "Y": 24, "Z": 89, "Datum": "22.93588"}, {"X": 11, "Y": 29, "Z": 93, "Datum": "21.485245"}, {"X": 11, "Y": 29, "Z": 94, "Datum": "23.798584"}, {"X": 11, "Y": 30, "Z": 93, "Datum": "48.764446"}, {"X": 11, "Y": 30, "Z": 94, "Datum": "33.49409"}, {"X": 11, "Y": 31, "Z": 93, "Datum": "25.804451"}, {"X": 11, "Y": 31, "Z": 94, "Datum": "15.333178"}, {"X": 12, "Y": 18, "Z": 84, "Datum": "21.611343"}, {"X": 12, "Y": 19, "Z": 83, "Datum": "19.926727"}, {"X": 12, "Y": 19, "Z": 84, "Datum": "44.499958"}, {"X": 12, "Y": 19, "Z": 85, "Datum": "25.952377"}, {"X": 12, "Y": 20, "Z": 83, "Datum": "15.263955"}, {"X": 12, "Y": 20, "Z": 84, "Datum": "71.60834"}, {"X": 12, "Y": 20, "Z": 85, "Datum": "63.257263"}, {"X": 12, "Y": 20, "Z": 86, "Datum": "34.360943"}, {"X": 12, "Y": 20, "Z": 87, "Datum": "19.199078"}, {"X": 12, "Y": 21, "Z": 83, "Datum": "17.084085"}, {"X": 12, "Y": 21, "Z": 84, "Datum": "84.91908"}, {"X": 12, "Y": 21, "Z": 85, "Datum": "85.86602"}, {"X": 12, "Y": 21, "Z": 86, "Datum": "71.64973"}, {"X": 12, "Y": 21, "Z": 87, "Datum": "46.7431"}, {"X": 12, "Y": 22, "Z": 83, "Datum": "16.98685"}, {"X": 12, "Y": 22, "Z": 84, "Datum": "46.936646"}, {"X": 12, "Y": 22, "Z": 85, "Datum": "65.37942"}, {"X": 12, "Y": 22, "Z": 86, "Datum": "78.775856"}, {"X": 12, "Y": 22, "Z": 87, "Datum": "47.05294"}, {"X": 12, "Y": 23, "Z": 83, "Datum": "16.40186"}, {"X": 12, "Y": 23, "Z": 84, "Datum": "31.882359"}, {"X": 12, "Y": 23, "Z": 85, "Datum": "49.97189"}, {"X": 12, "Y": 23, "Z": 86, "Datum": "62.220352"}, {"X": 12, "Y": 23, "Z": 87, "Datum": "44.617096"}, {"X": 12, "Y": 23, "Z": 88, "Datum": "26.798876"}, {"X": 12, "Y": 24, "Z": 84, "Datum": "18.06905"}, {"X": 12, "Y": 24, "Z": 85, "Datum": "28.84461"}, {"X": 12, "Y": 24, "Z": 86, "Datum": "50.899876"}, {"X": 12, "Y": 24, "Z": 87, "Datum": "55.07375"}, {"X": 12, "Y": 24, "Z": 88, "Datum": "38.01215"}, {"X": 12, "Y": 25, "Z": 85, "Datum": "21.932325"}, {"X": 12, "Y": 25, "Z": 86, "Datum": "52.464985"}, {"X": 12, "Y": 25, "Z": 87, "Datum": "58.001453"}, {"X": 12, "Y": 25, "Z": 88, "Datum": "24.975393"}, {"X": 12, "Y": 26, "Z": 85, "Datum": "17.631943"}, {"X": 12, "Y": 26, "Z": 86, "Datum": "78.20599"}, {"X": 12, "Y": 26, "Z": 87, "Datum": "74.40038"}, {"X": 12, "Y": 26, "Z": 88, "Datum": "27.683462"}, {"X": 12, "Y": 27, "Z": 86, "Datum": "137.20685"}, {"X": 12, "Y": 27, "Z": 87, "Datum": "105.160995"}, {"X": 12, "Y": 27, "Z": 88, "Datum": "61.441624"}, {"X": 12, "Y": 27, "Z": 89, "Datum": "29.422045"}, {"X": 12, "Y": 28, "Z": 86, "Datum": "96.51816"}, {"X": 12, "Y": 28, "Z": 87, "Datum": "85.05712"}, {"X": 12, "Y": 28, "Z": 88, "Datum": "70.440636"}, {"X": 12, "Y": 28, "Z": 89, "Datum": "50.60619"}, {"X": 12, "Y": 28, "Z": 90, "Datum": "25.867395"}, {"X": 12, "Y": 29, "Z": 86, "Datum": "31.709713"}, {"X": 12, "Y": 29, "Z": 87, "Datum": "27.74111"}, {"X": 12, "Y": 29, "Z": 88, "Datum": "29.12497"}, {"X": 12, "Y": 29, "Z": 89, "Datum": "41.412983"}, {"X": 12, "Y": 29, "Z": 90, "Datum": "55.175755"}, {"X": 12, "Y": 29, "Z": 91, "Datum": "39.202095"}, {"X": 12, "Y": 30, "Z": 89, "Datum": "35.815495"}, {"X": 12, "Y": 30, "Z": 90, "Datum": "71.13084"}, {"X": 12, "Y": 30, "Z": 91, "Datum": "67.722786"}, {"X": 12, "Y": 30, "Z": 92, "Datum": "33.331604"}, {"X": 12, "Y": 30, "Z": 93, "Datum": "25.274729"}, {"X": 12, "Y": 30, "Z": 94, "Datum": "17.913185"}, {"X": 12, "Y": 31, "Z": 89, "Datum": "32.16061"}, {"X": 12, "Y": 31, "Z": 90, "Datum": "54.16262"}, {"X": 12, "Y": 31, "Z": 91, "Datum": "52.76036"}, {"X": 12, "Y": 31, "Z": 92, "Datum": "33.7546"}, {"X": 12, "Y": 31, "Z": 93, "Datum": "19.825867"}, {"X": 12, "Y": 32, "Z": 89, "Datum": "17.709293"}, {"X": 12, "Y": 32, "Z": 90, "Datum": "16.585442"}, {"X": 13, "Y": 19, "Z": 83, "Datum": "15.858288"}, {"X": 13, "Y": 21, "Z": 84, "Datum": "23.66941"}, {"X": 13, "Y": 21, "Z": 85, "Datum": "21.286123"}, {"X": 13, "Y": 22, "Z": 84, "Datum": "26.555643"}, {"X": 13, "Y": 22, "Z": 85, "Datum": "34.07884"}, {"X": 13, "Y": 22, "Z": 86, "Datum": "23.396925"}, {"X": 13, "Y": 23, "Z": 84, "Datum": "18.694633"}, {"X": 13, "Y": 23, "Z": 85, "Datum": "27.329203"}, {"X": 13, "Y": 23, "Z": 86, "Datum": "25.354055"}, {"X": 13, "Y": 24, "Z": 85, "Datum": "17.204996"}, {"X": 13, "Y": 24, "Z": 86, "Datum": "26.777412"}, {"X": 13, "Y": 24, "Z": 87, "Datum": "21.698664"}, {"X": 13, "Y": 25, "Z": 86, "Datum": "28.747484"}, {"X": 13, "Y": 25, "Z": 87, "Datum": "30.700748"}, {"X": 13, "Y": 26, "Z": 86, "Datum": "37.75599"}, {"X": 13, "Y": 26, "Z": 87, "Datum": "40.12362"}, {"X": 13, "Y": 27, "Z": 86, "Datum": "51.28237"}, {"X": 13, "Y": 27, "Z": 87, "Datum": "55.752514"}, {"X": 13, "Y": 27, "Z": 88, "Datum": "32.38964"}, {"X": 13, "Y": 27, "Z": 89, "Datum": "15.561153"}, {"X": 13, "Y": 28, "Z": 86, "Datum": "39.1712"}, {"X": 13, "Y": 28, "Z": 87, "Datum": "46.331676"}, {"X": 13, "Y": 28, "Z": 88, "Datum": "37.105915"}, {"X": 13, "Y": 28, "Z": 89, "Datum": "26.455788"}, {"X": 13, "Y": 29, "Z": 86, "Datum": "16.122732"}, {"X": 13, "Y": 29, "Z": 87, "Datum": "17.034443"}, {"X": 13, "Y": 29, "Z": 88, "Datum": "16.363483"}, {"X": 13, "Y": 29, "Z": 89, "Datum": "22.179987"}, {"X": 13, "Y": 29, "Z": 90, "Datum": "28.620882"}, {"X": 13, "Y": 29, "Z": 91, "Datum": "20.44557"}, {"X": 13, "Y": 30, "Z": 89, "Datum": "20.738842"}, {"X": 13, "Y": 30, "Z": 90, "Datum": "37.758114"}, {"X": 13, "Y": 30, "Z": 91, "Datum": "35.378315"}, {"X": 13, "Y": 30, "Z": 92, "Datum": "17.178072"}, {"X": 13, "Y": 31, "Z": 89, "Datum": "19.393984"}, {"X": 13, "Y": 31, "Z": 90, "Datum": "29.238707"}, {"X": 13, "Y": 31, "Z": 91, "Datum": "27.68349"}, {"X": 13, "Y": 31, "Z": 92, "Datum": "17.428133"}], "smoke": []}