{"fire": [{"X": 5, "Y": 2, "Z": 87, "Datum": "23.20446"}, {"X": 5, "Y": 3, "Z": 87, "Datum": "23.92819"}, {"X": 5, "Y": 4, "Z": 87, "Datum": "18.17596"}, {"X": 5, "Y": 8, "Z": 93, "Datum": "17.428583"}, {"X": 5, "Y": 10, "Z": 95, "Datum": "16.875782"}, {"X": 5, "Y": 10, "Z": 96, "Datum": "19.114937"}, {"X": 5, "Y": 11, "Z": 95, "Datum": "18.102356"}, {"X": 5, "Y": 11, "Z": 96, "Datum": "24.220997"}, {"X": 6, "Y": 2, "Z": 83, "Datum": "16.36847"}, {"X": 10, "Y": 3, "Z": 60, "Datum": "23.781765"}, {"X": 10, "Y": 4, "Z": 60, "Datum": "50.514866"}, {"X": 10, "Y": 4, "Z": 61, "Datum": "28.982306"}, {"X": 10, "Y": 5, "Z": 60, "Datum": "28.940086"}, {"X": 10, "Y": 5, "Z": 61, "Datum": "24.970394"}, {"X": 10, "Y": 6, "Z": 58, "Datum": "34.174416"}, {"X": 10, "Y": 6, "Z": 59, "Datum": "19.830338"}, {"X": 10, "Y": 7, "Z": 58, "Datum": "38.771347"}, {"X": 10, "Y": 7, "Z": 59, "Datum": "30.303797"}, {"X": 10, "Y": 8, "Z": 57, "Datum": "18.764317"}, {"X": 10, "Y": 8, "Z": 58, "Datum": "37.095905"}, {"X": 10, "Y": 8, "Z": 59, "Datum": "25.960344"}, {"X": 10, "Y": 9, "Z": 57, "Datum": "24.113611"}, {"X": 10, "Y": 9, "Z": 58, "Datum": "30.823528"}, {"X": 10, "Y": 31, "Z": 59, "Datum": "31.808168"}, {"X": 10, "Y": 31, "Z": 60, "Datum": "17.578842"}, {"X": 10, "Y": 32, "Z": 57, "Datum": "66.453285"}, {"X": 10, "Y": 32, "Z": 58, "Datum": "81.75401"}, {"X": 10, "Y": 32, "Z": 59, "Datum": "72.22515"}, {"X": 10, "Y": 32, "Z": 60, "Datum": "31.553621"}, {"X": 10, "Y": 33, "Z": 57, "Datum": "66.453285"}, {"X": 10, "Y": 33, "Z": 58, "Datum": "81.75401"}, {"X": 10, "Y": 33, "Z": 59, "Datum": "90.101875"}, {"X": 10, "Y": 33, "Z": 60, "Datum": "60.201344"}, {"X": 10, "Y": 33, "Z": 61, "Datum": "25.826122"}, {"X": 10, "Y": 33, "Z": 62, "Datum": "23.267088"}, {"X": 10, "Y": 33, "Z": 63, "Datum": "28.659174"}, {"X": 10, "Y": 34, "Z": 59, "Datum": "150.20326"}, {"X": 10, "Y": 34, "Z": 60, "Datum": "124.11475"}, {"X": 10, "Y": 34, "Z": 61, "Datum": "86.41536"}, {"X": 10, "Y": 34, "Z": 62, "Datum": "84.12048"}, {"X": 10, "Y": 34, "Z": 63, "Datum": "93.43651"}, {"X": 10, "Y": 35, "Z": 59, "Datum": "102.536476"}, {"X": 10, "Y": 35, "Z": 60, "Datum": "144.92772"}, {"X": 10, "Y": 35, "Z": 61, "Datum": "123.34956"}, {"X": 10, "Y": 35, "Z": 62, "Datum": "122.10839"}, {"X": 10, "Y": 35, "Z": 63, "Datum": "129.80275"}, {"X": 10, "Y": 36, "Z": 59, "Datum": "60.0506"}, {"X": 10, "Y": 36, "Z": 60, "Datum": "87.5202"}, {"X": 10, "Y": 37, "Z": 59, "Datum": "41.22932"}, {"X": 10, "Y": 37, "Z": 60, "Datum": "41.22932"}, {"X": 10, "Y": 38, "Z": 59, "Datum": "21.763716"}, {"X": 10, "Y": 38, "Z": 60, "Datum": "21.763716"}, {"X": 11, "Y": 0, "Z": 61, "Datum": "15.542178"}, {"X": 11, "Y": 0, "Z": 62, "Datum": "28.716375"}, {"X": 11, "Y": 0, "Z": 63, "Datum": "21.12526"}, {"X": 11, "Y": 1, "Z": 60, "Datum": "30.587795"}, {"X": 11, "Y": 1, "Z": 61, "Datum": "34.250187"}, {"X": 11, "Y": 1, "Z": 62, "Datum": "32.66467"}, {"X": 11, "Y": 1, "Z": 63, "Datum": "18.122883"}, {"X": 11, "Y": 2, "Z": 59, "Datum": "112.88655"}, {"X": 11, "Y": 2, "Z": 60, "Datum": "75.181885"}, {"X": 11, "Y": 2, "Z": 61, "Datum": "46.803684"}, {"X": 11, "Y": 2, "Z": 62, "Datum": "27.824532"}, {"X": 11, "Y": 3, "Z": 57, "Datum": "17.582497"}, {"X": 11, "Y": 3, "Z": 58, "Datum": "42.327686"}, {"X": 11, "Y": 3, "Z": 59, "Datum": "72.20445"}, {"X": 11, "Y": 3, "Z": 60, "Datum": "51.869312"}, {"X": 11, "Y": 3, "Z": 61, "Datum": "24.686493"}, {"X": 11, "Y": 4, "Z": 57, "Datum": "16.787056"}, {"X": 11, "Y": 4, "Z": 58, "Datum": "36.275864"}, {"X": 11, "Y": 4, "Z": 59, "Datum": "52.334934"}, {"X": 11, "Y": 4, "Z": 60, "Datum": "41.10374"}, {"X": 11, "Y": 4, "Z": 61, "Datum": "21.993324"}, {"X": 11, "Y": 5, "Z": 57, "Datum": "22.823912"}, {"X": 11, "Y": 5, "Z": 58, "Datum": "33.189915"}, {"X": 11, "Y": 5, "Z": 59, "Datum": "32.249264"}, {"X": 11, "Y": 5, "Z": 60, "Datum": "28.236523"}, {"X": 11, "Y": 5, "Z": 61, "Datum": "15.486828"}, {"X": 11, "Y": 6, "Z": 57, "Datum": "17.248623"}, {"X": 11, "Y": 6, "Z": 58, "Datum": "28.168074"}, {"X": 11, "Y": 6, "Z": 59, "Datum": "17.712713"}, {"X": 11, "Y": 7, "Z": 58, "Datum": "24.960732"}, {"X": 11, "Y": 7, "Z": 59, "Datum": "17.656782"}, {"X": 11, "Y": 8, "Z": 58, "Datum": "22.197123"}, {"X": 11, "Y": 9, "Z": 58, "Datum": "21.710972"}, {"X": 11, "Y": 10, "Z": 58, "Datum": "39.208374"}, {"X": 11, "Y": 10, "Z": 59, "Datum": "19.238066"}, {"X": 11, "Y": 11, "Z": 57, "Datum": "22.940899"}, {"X": 11, "Y": 11, "Z": 58, "Datum": "57.993557"}, {"X": 11, "Y": 11, "Z": 59, "Datum": "34.356403"}, {"X": 11, "Y": 12, "Z": 57, "Datum": "40.247356"}, {"X": 11, "Y": 12, "Z": 58, "Datum": "65.40928"}, {"X": 11, "Y": 12, "Z": 59, "Datum": "30.774979"}, {"X": 11, "Y": 20, "Z": 59, "Datum": "81.7491"}, {"X": 11, "Y": 20, "Z": 60, "Datum": "33.019054"}, {"X": 11, "Y": 21, "Z": 59, "Datum": "59.56684"}, {"X": 11, "Y": 21, "Z": 60, "Datum": "29.43538"}, {"X": 11, "Y": 22, "Z": 59, "Datum": "23.270023"}, {"X": 11, "Y": 29, "Z": 57, "Datum": "132.66664"}, {"X": 11, "Y": 29, "Z": 58, "Datum": "115.28533"}, {"X": 11, "Y": 29, "Z": 59, "Datum": "21.92615"}, {"X": 11, "Y": 30, "Z": 57, "Datum": "111.02252"}, {"X": 11, "Y": 30, "Z": 58, "Datum": "102.93796"}, {"X": 11, "Y": 30, "Z": 59, "Datum": "34.090813"}, {"X": 11, "Y": 31, "Z": 57, "Datum": "57.975983"}, {"X": 11, "Y": 31, "Z": 58, "Datum": "66.801544"}, {"X": 11, "Y": 31, "Z": 59, "Datum": "37.072247"}, {"X": 11, "Y": 32, "Z": 57, "Datum": "35.81749"}, {"X": 11, "Y": 32, "Z": 58, "Datum": "52.75548"}, {"X": 11, "Y": 32, "Z": 59, "Datum": "44.691936"}, {"X": 11, "Y": 32, "Z": 60, "Datum": "16.848663"}, {"X": 11, "Y": 33, "Z": 57, "Datum": "37.313164"}, {"X": 11, "Y": 33, "Z": 58, "Datum": "56.75971"}, {"X": 11, "Y": 33, "Z": 59, "Datum": "50.3328"}, {"X": 11, "Y": 33, "Z": 60, "Datum": "31.246746"}, {"X": 11, "Y": 33, "Z": 63, "Datum": "22.374578"}, {"X": 11, "Y": 33, "Z": 64, "Datum": "55.665707"}, {"X": 11, "Y": 33, "Z": 65, "Datum": "74.698364"}, {"X": 11, "Y": 34, "Z": 57, "Datum": "23.700275"}, {"X": 11, "Y": 34, "Z": 58, "Datum": "38.65544"}, {"X": 11, "Y": 34, "Z": 59, "Datum": "64.535545"}, {"X": 11, "Y": 34, "Z": 60, "Datum": "64.732635"}, {"X": 11, "Y": 34, "Z": 61, "Datum": "44.81372"}, {"X": 11, "Y": 34, "Z": 62, "Datum": "45.432964"}, {"X": 11, "Y": 34, "Z": 63, "Datum": "57.673534"}, {"X": 11, "Y": 34, "Z": 64, "Datum": "86.16935"}, {"X": 11, "Y": 34, "Z": 65, "Datum": "103.27612"}, {"X": 11, "Y": 35, "Z": 59, "Datum": "56.805496"}, {"X": 11, "Y": 35, "Z": 60, "Datum": "70.21344"}, {"X": 11, "Y": 35, "Z": 61, "Datum": "44.20014"}, {"X": 11, "Y": 35, "Z": 62, "Datum": "47.008602"}, {"X": 11, "Y": 35, "Z": 63, "Datum": "56.801167"}, {"X": 11, "Y": 35, "Z": 64, "Datum": "77.83551"}, {"X": 11, "Y": 35, "Z": 65, "Datum": "87.44494"}, {"X": 11, "Y": 35, "Z": 66, "Datum": "76.11354"}, {"X": 11, "Y": 36, "Z": 59, "Datum": "37.985653"}, {"X": 11, "Y": 36, "Z": 60, "Datum": "39.710724"}, {"X": 11, "Y": 36, "Z": 63, "Datum": "19.050665"}, {"X": 11, "Y": 36, "Z": 64, "Datum": "55.18597"}, {"X": 11, "Y": 36, "Z": 65, "Datum": "61.46704"}, {"X": 11, "Y": 36, "Z": 66, "Datum": "31.527227"}, {"X": 11, "Y": 36, "Z": 67, "Datum": "20.53153"}, {"X": 11, "Y": 36, "Z": 68, "Datum": "32.347973"}, {"X": 11, "Y": 37, "Z": 59, "Datum": "23.340258"}, {"X": 11, "Y": 37, "Z": 60, "Datum": "19.877197"}, {"X": 11, "Y": 37, "Z": 64, "Datum": "40.161453"}, {"X": 11, "Y": 37, "Z": 65, "Datum": "44.387077"}, {"X": 11, "Y": 37, "Z": 66, "Datum": "33.11563"}, {"X": 11, "Y": 37, "Z": 67, "Datum": "35.671272"}, {"X": 11, "Y": 37, "Z": 68, "Datum": "34.497444"}, {"X": 11, "Y": 38, "Z": 63, "Datum": "27.140923"}, {"X": 11, "Y": 38, "Z": 64, "Datum": "70.53373"}, {"X": 11, "Y": 38, "Z": 65, "Datum": "103.263504"}, {"X": 11, "Y": 38, "Z": 66, "Datum": "95.04187"}, {"X": 11, "Y": 38, "Z": 67, "Datum": "50.811016"}, {"X": 11, "Y": 38, "Z": 68, "Datum": "36.64692"}, {"X": 11, "Y": 38, "Z": 95, "Datum": "16.872444"}, {"X": 11, "Y": 38, "Z": 96, "Datum": "25.018875"}, {"X": 11, "Y": 39, "Z": 63, "Datum": "38.694912"}, {"X": 11, "Y": 39, "Z": 64, "Datum": "98.86703"}, {"X": 11, "Y": 39, "Z": 65, "Datum": "153.0707"}, {"X": 11, "Y": 39, "Z": 66, "Datum": "171.13124"}, {"X": 11, "Y": 39, "Z": 95, "Datum": "49.13515"}, {"X": 11, "Y": 39, "Z": 96, "Datum": "49.13515"}, {"X": 12, "Y": 1, "Z": 60, "Datum": "16.993309"}, {"X": 12, "Y": 1, "Z": 61, "Datum": "17.32804"}, {"X": 12, "Y": 1, "Z": 62, "Datum": "16.4169"}, {"X": 12, "Y": 2, "Z": 58, "Datum": "21.237638"}, {"X": 12, "Y": 2, "Z": 59, "Datum": "48.73771"}, {"X": 12, "Y": 2, "Z": 60, "Datum": "41.117634"}, {"X": 12, "Y": 2, "Z": 61, "Datum": "23.751833"}, {"X": 12, "Y": 3, "Z": 58, "Datum": "34.090557"}, {"X": 12, "Y": 3, "Z": 59, "Datum": "48.304935"}, {"X": 12, "Y": 3, "Z": 60, "Datum": "33.36895"}, {"X": 12, "Y": 3, "Z": 61, "Datum": "15.894381"}, {"X": 12, "Y": 4, "Z": 58, "Datum": "25.928888"}, {"X": 12, "Y": 4, "Z": 59, "Datum": "32.644077"}, {"X": 12, "Y": 4, "Z": 60, "Datum": "19.92812"}, {"X": 12, "Y": 5, "Z": 58, "Datum": "20.312435"}, {"X": 12, "Y": 5, "Z": 59, "Datum": "22.160109"}, {"X": 12, "Y": 5, "Z": 60, "Datum": "15.022445"}, {"X": 12, "Y": 6, "Z": 58, "Datum": "15.093731"}, {"X": 12, "Y": 10, "Z": 58, "Datum": "20.95706"}, {"X": 12, "Y": 11, "Z": 58, "Datum": "31.725138"}, {"X": 12, "Y": 11, "Z": 59, "Datum": "22.034643"}, {"X": 12, "Y": 12, "Z": 57, "Datum": "18.17266"}, {"X": 12, "Y": 12, "Z": 58, "Datum": "35.00423"}, {"X": 12, "Y": 12, "Z": 59, "Datum": "19.496258"}, {"X": 12, "Y": 13, "Z": 57, "Datum": "18.565723"}, {"X": 12, "Y": 13, "Z": 58, "Datum": "25.934856"}, {"X": 12, "Y": 14, "Z": 56, "Datum": "18.43964"}, {"X": 12, "Y": 14, "Z": 57, "Datum": "40.195084"}, {"X": 12, "Y": 14, "Z": 58, "Datum": "30.007433"}, {"X": 12, "Y": 15, "Z": 57, "Datum": "80.0975"}, {"X": 12, "Y": 15, "Z": 58, "Datum": "49.908836"}, {"X": 12, "Y": 16, "Z": 57, "Datum": "169.37843"}, {"X": 12, "Y": 16, "Z": 58, "Datum": "126.45802"}, {"X": 12, "Y": 16, "Z": 59, "Datum": "44.86514"}, {"X": 12, "Y": 17, "Z": 57, "Datum": "253.6202"}, {"X": 12, "Y": 17, "Z": 58, "Datum": "192.62292"}, {"X": 12, "Y": 17, "Z": 59, "Datum": "49.890583"}, {"X": 12, "Y": 20, "Z": 57, "Datum": "55.60887"}, {"X": 12, "Y": 20, "Z": 58, "Datum": "31.617846"}, {"X": 12, "Y": 20, "Z": 59, "Datum": "19.577562"}, {"X": 12, "Y": 21, "Z": 57, "Datum": "107.624306"}, {"X": 12, "Y": 21, "Z": 58, "Datum": "66.46752"}, {"X": 12, "Y": 21, "Z": 59, "Datum": "29.300116"}, {"X": 12, "Y": 21, "Z": 60, "Datum": "19.168148"}, {"X": 12, "Y": 22, "Z": 57, "Datum": "89.377365"}, {"X": 12, "Y": 22, "Z": 58, "Datum": "67.116776"}, {"X": 12, "Y": 22, "Z": 59, "Datum": "24.095423"}, {"X": 12, "Y": 23, "Z": 57, "Datum": "80.5514"}, {"X": 12, "Y": 23, "Z": 58, "Datum": "66.91916"}, {"X": 12, "Y": 23, "Z": 59, "Datum": "20.227182"}, {"X": 12, "Y": 24, "Z": 57, "Datum": "128.114"}, {"X": 12, "Y": 24, "Z": 58, "Datum": "89.6845"}, {"X": 12, "Y": 24, "Z": 59, "Datum": "17.728321"}, {"X": 12, "Y": 25, "Z": 57, "Datum": "154.31503"}, {"X": 12, "Y": 25, "Z": 58, "Datum": "95.0861"}, {"X": 12, "Y": 26, "Z": 57, "Datum": "142.90549"}, {"X": 12, "Y": 26, "Z": 58, "Datum": "78.52801"}, {"X": 12, "Y": 27, "Z": 57, "Datum": "131.92343"}, {"X": 12, "Y": 27, "Z": 58, "Datum": "68.17621"}, {"X": 12, "Y": 28, "Z": 57, "Datum": "123.394165"}, {"X": 12, "Y": 28, "Z": 58, "Datum": "63.01739"}, {"X": 12, "Y": 29, "Z": 56, "Datum": "33.024902"}, {"X": 12, "Y": 29, "Z": 57, "Datum": "91.525406"}, {"X": 12, "Y": 29, "Z": 58, "Datum": "72.77895"}, {"X": 12, "Y": 29, "Z": 59, "Datum": "15.076416"}, {"X": 12, "Y": 30, "Z": 56, "Datum": "25.146114"}, {"X": 12, "Y": 30, "Z": 57, "Datum": "64.90242"}, {"X": 12, "Y": 30, "Z": 58, "Datum": "66.84251"}, {"X": 12, "Y": 30, "Z": 59, "Datum": "25.17511"}, {"X": 12, "Y": 31, "Z": 57, "Datum": "29.781635"}, {"X": 12, "Y": 31, "Z": 58, "Datum": "38.88873"}, {"X": 12, "Y": 31, "Z": 59, "Datum": "20.524685"}, {"X": 12, "Y": 32, "Z": 58, "Datum": "20.966663"}, {"X": 12, "Y": 33, "Z": 57, "Datum": "17.321644"}, {"X": 12, "Y": 33, "Z": 58, "Datum": "23.570715"}, {"X": 12, "Y": 33, "Z": 64, "Datum": "31.502993"}, {"X": 12, "Y": 33, "Z": 65, "Datum": "35.500923"}, {"X": 12, "Y": 34, "Z": 58, "Datum": "20.446798"}, {"X": 12, "Y": 34, "Z": 63, "Datum": "22.328526"}, {"X": 12, "Y": 34, "Z": 64, "Datum": "49.421352"}, {"X": 12, "Y": 34, "Z": 65, "Datum": "49.880116"}, {"X": 12, "Y": 35, "Z": 63, "Datum": "22.532503"}, {"X": 12, "Y": 35, "Z": 64, "Datum": "45.134857"}, {"X": 12, "Y": 35, "Z": 65, "Datum": "47.87993"}, {"X": 12, "Y": 35, "Z": 66, "Datum": "23.983007"}, {"X": 12, "Y": 35, "Z": 69, "Datum": "42.48769"}, {"X": 12, "Y": 36, "Z": 64, "Datum": "32.199165"}, {"X": 12, "Y": 36, "Z": 65, "Datum": "36.082962"}, {"X": 12, "Y": 36, "Z": 66, "Datum": "16.954397"}, {"X": 12, "Y": 36, "Z": 68, "Datum": "29.831646"}, {"X": 12, "Y": 36, "Z": 69, "Datum": "55.2767"}, {"X": 12, "Y": 36, "Z": 70, "Datum": "54.497063"}, {"X": 12, "Y": 36, "Z": 71, "Datum": "55.835808"}, {"X": 12, "Y": 37, "Z": 64, "Datum": "22.573254"}, {"X": 12, "Y": 37, "Z": 65, "Datum": "24.481369"}, {"X": 12, "Y": 37, "Z": 66, "Datum": "18.013445"}, {"X": 12, "Y": 37, "Z": 67, "Datum": "20.705492"}, {"X": 12, "Y": 37, "Z": 68, "Datum": "37.931976"}, {"X": 12, "Y": 37, "Z": 69, "Datum": "67.79301"}, {"X": 12, "Y": 37, "Z": 70, "Datum": "51.94527"}, {"X": 12, "Y": 37, "Z": 71, "Datum": "37.995815"}, {"X": 12, "Y": 38, "Z": 63, "Datum": "17.81686"}, {"X": 12, "Y": 38, "Z": 64, "Datum": "39.399826"}, {"X": 12, "Y": 38, "Z": 65, "Datum": "55.016365"}, {"X": 12, "Y": 38, "Z": 66, "Datum": "52.432755"}, {"X": 12, "Y": 38, "Z": 67, "Datum": "32.530518"}, {"X": 12, "Y": 38, "Z": 68, "Datum": "34.41031"}, {"X": 12, "Y": 38, "Z": 69, "Datum": "57.55016"}, {"X": 12, "Y": 38, "Z": 70, "Datum": "42.41516"}, {"X": 12, "Y": 38, "Z": 71, "Datum": "22.758781"}, {"X": 12, "Y": 39, "Z": 63, "Datum": "19.745419"}, {"X": 12, "Y": 39, "Z": 64, "Datum": "39.276478"}, {"X": 12, "Y": 39, "Z": 65, "Datum": "57.33768"}, {"X": 12, "Y": 39, "Z": 66, "Datum": "58.465416"}, {"X": 12, "Y": 39, "Z": 67, "Datum": "29.50529"}, {"X": 12, "Y": 39, "Z": 68, "Datum": "18.66626"}, {"X": 12, "Y": 39, "Z": 69, "Datum": "31.901604"}, {"X": 12, "Y": 39, "Z": 70, "Datum": "35.436848"}, {"X": 12, "Y": 39, "Z": 71, "Datum": "25.36174"}, {"X": 12, "Y": 39, "Z": 94, "Datum": "19.129354"}, {"X": 12, "Y": 39, "Z": 95, "Datum": "20.871542"}, {"X": 12, "Y": 39, "Z": 96, "Datum": "17.609442"}, {"X": 12, "Y": 40, "Z": 93, "Datum": "57.83063"}, {"X": 12, "Y": 40, "Z": 94, "Datum": "33.963955"}, {"X": 12, "Y": 41, "Z": 93, "Datum": "103.97502"}, {"X": 12, "Y": 41, "Z": 94, "Datum": "53.847885"}, {"X": 13, "Y": 2, "Z": 59, "Datum": "16.519552"}, {"X": 13, "Y": 3, "Z": 58, "Datum": "15.807333"}, {"X": 13, "Y": 3, "Z": 59, "Datum": "15.680676"}, {"X": 13, "Y": 14, "Z": 57, "Datum": "20.217587"}, {"X": 13, "Y": 14, "Z": 58, "Datum": "16.126848"}, {"X": 13, "Y": 15, "Z": 56, "Datum": "33.95604"}, {"X": 13, "Y": 15, "Z": 57, "Datum": "39.604115"}, {"X": 13, "Y": 15, "Z": 58, "Datum": "26.354895"}, {"X": 13, "Y": 16, "Z": 56, "Datum": "65.987144"}, {"X": 13, "Y": 16, "Z": 57, "Datum": "82.8162"}, {"X": 13, "Y": 16, "Z": 58, "Datum": "67.2708"}, {"X": 13, "Y": 16, "Z": 59, "Datum": "23.396954"}, {"X": 13, "Y": 17, "Z": 56, "Datum": "86.63763"}, {"X": 13, "Y": 17, "Z": 57, "Datum": "98.85612"}, {"X": 13, "Y": 17, "Z": 58, "Datum": "78.04933"}, {"X": 13, "Y": 17, "Z": 59, "Datum": "24.004978"}, {"X": 13, "Y": 18, "Z": 56, "Datum": "77.2892"}, {"X": 13, "Y": 18, "Z": 57, "Datum": "42.98794"}, {"X": 13, "Y": 19, "Z": 56, "Datum": "29.555607"}, {"X": 13, "Y": 19, "Z": 57, "Datum": "15.101312"}, {"X": 13, "Y": 20, "Z": 57, "Datum": "21.325104"}, {"X": 13, "Y": 20, "Z": 58, "Datum": "16.53336"}, {"X": 13, "Y": 21, "Z": 56, "Datum": "42.87174"}, {"X": 13, "Y": 21, "Z": 57, "Datum": "50.794598"}, {"X": 13, "Y": 21, "Z": 58, "Datum": "33.786297"}, {"X": 13, "Y": 22, "Z": 56, "Datum": "60.50317"}, {"X": 13, "Y": 22, "Z": 57, "Datum": "51.944027"}, {"X": 13, "Y": 22, "Z": 58, "Datum": "35.19871"}, {"X": 13, "Y": 23, "Z": 56, "Datum": "26.112211"}, {"X": 13, "Y": 23, "Z": 57, "Datum": "37.938534"}, {"X": 13, "Y": 23, "Z": 58, "Datum": "35.46168"}, {"X": 13, "Y": 24, "Z": 57, "Datum": "47.644745"}, {"X": 13, "Y": 24, "Z": 58, "Datum": "46.48466"}, {"X": 13, "Y": 25, "Z": 56, "Datum": "35.581978"}, {"X": 13, "Y": 25, "Z": 57, "Datum": "65.3166"}, {"X": 13, "Y": 25, "Z": 58, "Datum": "49.32425"}, {"X": 13, "Y": 26, "Z": 56, "Datum": "51.834328"}, {"X": 13, "Y": 26, "Z": 57, "Datum": "71.334305"}, {"X": 13, "Y": 26, "Z": 58, "Datum": "40.86937"}, {"X": 13, "Y": 27, "Z": 56, "Datum": "45.219196"}, {"X": 13, "Y": 27, "Z": 57, "Datum": "67.47406"}, {"X": 13, "Y": 27, "Z": 58, "Datum": "35.547195"}, {"X": 13, "Y": 28, "Z": 55, "Datum": "17.395525"}, {"X": 13, "Y": 28, "Z": 56, "Datum": "48.932304"}, {"X": 13, "Y": 28, "Z": 57, "Datum": "65.35682"}, {"X": 13, "Y": 28, "Z": 58, "Datum": "33.05844"}, {"X": 13, "Y": 29, "Z": 55, "Datum": "19.997025"}, {"X": 13, "Y": 29, "Z": 56, "Datum": "41.725975"}, {"X": 13, "Y": 29, "Z": 57, "Datum": "50.780563"}, {"X": 13, "Y": 29, "Z": 58, "Datum": "27.516064"}, {"X": 13, "Y": 30, "Z": 55, "Datum": "16.04031"}, {"X": 13, "Y": 30, "Z": 56, "Datum": "26.131218"}, {"X": 13, "Y": 30, "Z": 57, "Datum": "29.438505"}, {"X": 13, "Y": 30, "Z": 58, "Datum": "16.811884"}, {"X": 13, "Y": 33, "Z": 73, "Datum": "22.63713"}, {"X": 13, "Y": 33, "Z": 74, "Datum": "44.397507"}, {"X": 13, "Y": 34, "Z": 73, "Datum": "16.944174"}, {"X": 13, "Y": 34, "Z": 74, "Datum": "32.8525"}, {"X": 13, "Y": 35, "Z": 74, "Datum": "21.307499"}, {"X": 13, "Y": 36, "Z": 68, "Datum": "15.087543"}, {"X": 13, "Y": 36, "Z": 69, "Datum": "24.327019"}, {"X": 13, "Y": 36, "Z": 70, "Datum": "19.326048"}, {"X": 13, "Y": 37, "Z": 68, "Datum": "21.056845"}, {"X": 13, "Y": 37, "Z": 69, "Datum": "35.929626"}, {"X": 13, "Y": 37, "Z": 70, "Datum": "29.711437"}, {"X": 13, "Y": 37, "Z": 71, "Datum": "24.127316"}, {"X": 13, "Y": 38, "Z": 68, "Datum": "18.66189"}, {"X": 13, "Y": 38, "Z": 69, "Datum": "33.381268"}, {"X": 13, "Y": 38, "Z": 70, "Datum": "28.605452"}, {"X": 13, "Y": 38, "Z": 71, "Datum": "29.506195"}, {"X": 13, "Y": 38, "Z": 72, "Datum": "27.673899"}, {"X": 13, "Y": 39, "Z": 66, "Datum": "15.857323"}, {"X": 13, "Y": 39, "Z": 67, "Datum": "16.061577"}, {"X": 13, "Y": 39, "Z": 69, "Datum": "19.490591"}, {"X": 13, "Y": 39, "Z": 70, "Datum": "33.638557"}, {"X": 13, "Y": 39, "Z": 71, "Datum": "39.87107"}, {"X": 13, "Y": 39, "Z": 72, "Datum": "21.882116"}, {"X": 13, "Y": 40, "Z": 70, "Datum": "42.92975"}, {"X": 13, "Y": 40, "Z": 71, "Datum": "42.299507"}, {"X": 13, "Y": 40, "Z": 93, "Datum": "24.31106"}, {"X": 13, "Y": 40, "Z": 94, "Datum": "19.595503"}, {"X": 13, "Y": 41, "Z": 69, "Datum": "25.529125"}, {"X": 13, "Y": 41, "Z": 70, "Datum": "60.142017"}, {"X": 13, "Y": 41, "Z": 71, "Datum": "56.581257"}, {"X": 13, "Y": 41, "Z": 72, "Datum": "26.954916"}, {"X": 13, "Y": 41, "Z": 92, "Datum": "15.038374"}, {"X": 13, "Y": 41, "Z": 93, "Datum": "33.809296"}, {"X": 13, "Y": 41, "Z": 94, "Datum": "21.162745"}, {"X": 13, "Y": 42, "Z": 68, "Datum": "15.128246"}, {"X": 13, "Y": 42, "Z": 69, "Datum": "44.05963"}, {"X": 13, "Y": 42, "Z": 70, "Datum": "70.90573"}, {"X": 13, "Y": 42, "Z": 71, "Datum": "78.28085"}, {"X": 13, "Y": 42, "Z": 72, "Datum": "76.41883"}, {"X": 13, "Y": 42, "Z": 91, "Datum": "20.626633"}, {"X": 13, "Y": 42, "Z": 92, "Datum": "28.877275"}, {"X": 13, "Y": 43, "Z": 69, "Datum": "25.210379"}, {"X": 13, "Y": 43, "Z": 70, "Datum": "41.582027"}, {"X": 13, "Y": 43, "Z": 71, "Datum": "48.957333"}, {"X": 13, "Y": 43, "Z": 86, "Datum": "51.792686"}, {"X": 13, "Y": 43, "Z": 87, "Datum": "49.862774"}, {"X": 13, "Y": 43, "Z": 88, "Datum": "40.437935"}, {"X": 13, "Y": 43, "Z": 89, "Datum": "34.21784"}, {"X": 13, "Y": 43, "Z": 90, "Datum": "38.20301"}, {"X": 13, "Y": 43, "Z": 91, "Datum": "37.61829"}, {"X": 13, "Y": 43, "Z": 92, "Datum": "19.93041"}, {"X": 13, "Y": 44, "Z": 85, "Datum": "21.593168"}, {"X": 13, "Y": 44, "Z": 86, "Datum": "61.640358"}, {"X": 13, "Y": 44, "Z": 87, "Datum": "70.039894"}, {"X": 13, "Y": 44, "Z": 88, "Datum": "75.78324"}, {"X": 13, "Y": 44, "Z": 89, "Datum": "74.58851"}, {"X": 13, "Y": 44, "Z": 90, "Datum": "48.98009"}, {"X": 13, "Y": 44, "Z": 91, "Datum": "21.313372"}, {"X": 13, "Y": 45, "Z": 86, "Datum": "27.593395"}, {"X": 13, "Y": 45, "Z": 87, "Datum": "40.033554"}, {"X": 13, "Y": 45, "Z": 88, "Datum": "59.95557"}, {"X": 13, "Y": 45, "Z": 89, "Datum": "50.641216"}, {"X": 13, "Y": 45, "Z": 90, "Datum": "15.184915"}, {"X": 13, "Y": 46, "Z": 88, "Datum": "17.930223"}, {"X": 14, "Y": 16, "Z": 56, "Datum": "23.105566"}, {"X": 14, "Y": 16, "Z": 57, "Datum": "20.362408"}, {"X": 14, "Y": 17, "Z": 56, "Datum": "30.33936"}, {"X": 14, "Y": 17, "Z": 57, "Datum": "30.933777"}, {"X": 14, "Y": 18, "Z": 56, "Datum": "30.84749"}, {"X": 14, "Y": 18, "Z": 57, "Datum": "29.827475"}, {"X": 14, "Y": 19, "Z": 55, "Datum": "17.428968"}, {"X": 14, "Y": 19, "Z": 56, "Datum": "23.332293"}, {"X": 14, "Y": 20, "Z": 55, "Datum": "41.56402"}, {"X": 14, "Y": 20, "Z": 56, "Datum": "24.549753"}, {"X": 14, "Y": 21, "Z": 54, "Datum": "17.373652"}, {"X": 14, "Y": 21, "Z": 55, "Datum": "53.53636"}, {"X": 14, "Y": 21, "Z": 56, "Datum": "39.986763"}, {"X": 14, "Y": 22, "Z": 54, "Datum": "19.099697"}, {"X": 14, "Y": 22, "Z": 55, "Datum": "42.77423"}, {"X": 14, "Y": 22, "Z": 56, "Datum": "39.36891"}, {"X": 14, "Y": 22, "Z": 57, "Datum": "18.112436"}, {"X": 14, "Y": 23, "Z": 55, "Datum": "21.626877"}, {"X": 14, "Y": 23, "Z": 56, "Datum": "18.040293"}, {"X": 14, "Y": 26, "Z": 56, "Datum": "23.759098"}, {"X": 14, "Y": 26, "Z": 57, "Datum": "18.59743"}, {"X": 14, "Y": 27, "Z": 56, "Datum": "23.968266"}, {"X": 14, "Y": 27, "Z": 57, "Datum": "18.265913"}, {"X": 14, "Y": 28, "Z": 56, "Datum": "26.071957"}, {"X": 14, "Y": 28, "Z": 57, "Datum": "18.606924"}, {"X": 14, "Y": 29, "Z": 56, "Datum": "24.618452"}, {"X": 14, "Y": 29, "Z": 57, "Datum": "16.141531"}, {"X": 14, "Y": 30, "Z": 56, "Datum": "16.501602"}, {"X": 14, "Y": 38, "Z": 71, "Datum": "17.152742"}, {"X": 14, "Y": 39, "Z": 70, "Datum": "18.009735"}, {"X": 14, "Y": 39, "Z": 71, "Datum": "22.72946"}, {"X": 14, "Y": 40, "Z": 70, "Datum": "22.75385"}, {"X": 14, "Y": 40, "Z": 71, "Datum": "21.798914"}, {"X": 14, "Y": 41, "Z": 69, "Datum": "16.687286"}, {"X": 14, "Y": 41, "Z": 70, "Datum": "31.031296"}, {"X": 14, "Y": 41, "Z": 71, "Datum": "29.156557"}, {"X": 14, "Y": 42, "Z": 69, "Datum": "23.906464"}, {"X": 14, "Y": 42, "Z": 70, "Datum": "39.322754"}, {"X": 14, "Y": 42, "Z": 71, "Datum": "46.555508"}, {"X": 14, "Y": 42, "Z": 72, "Datum": "43.300766"}, {"X": 14, "Y": 42, "Z": 73, "Datum": "29.707489"}, {"X": 14, "Y": 42, "Z": 74, "Datum": "16.853987"}, {"X": 14, "Y": 42, "Z": 92, "Datum": "15.1973505"}, {"X": 14, "Y": 43, "Z": 70, "Datum": "26.541674"}, {"X": 14, "Y": 43, "Z": 71, "Datum": "39.728596"}, {"X": 14, "Y": 43, "Z": 72, "Datum": "61.667828"}, {"X": 14, "Y": 43, "Z": 73, "Datum": "50.270107"}, {"X": 14, "Y": 43, "Z": 74, "Datum": "32.04442"}, {"X": 14, "Y": 43, "Z": 86, "Datum": "21.252882"}, {"X": 14, "Y": 43, "Z": 87, "Datum": "25.554985"}, {"X": 14, "Y": 43, "Z": 88, "Datum": "20.939337"}, {"X": 14, "Y": 43, "Z": 89, "Datum": "18.154573"}, {"X": 14, "Y": 43, "Z": 90, "Datum": "20.720598"}, {"X": 14, "Y": 43, "Z": 91, "Datum": "20.23033"}, {"X": 14, "Y": 44, "Z": 71, "Datum": "17.159817"}, {"X": 14, "Y": 44, "Z": 72, "Datum": "40.31212"}, {"X": 14, "Y": 44, "Z": 73, "Datum": "31.578466"}, {"X": 14, "Y": 44, "Z": 83, "Datum": "23.762577"}, {"X": 14, "Y": 44, "Z": 84, "Datum": "17.34754"}, {"X": 14, "Y": 44, "Z": 85, "Datum": "18.25238"}, {"X": 14, "Y": 44, "Z": 86, "Datum": "33.99783"}, {"X": 14, "Y": 44, "Z": 87, "Datum": "38.358315"}, {"X": 14, "Y": 44, "Z": 88, "Datum": "40.258614"}, {"X": 14, "Y": 44, "Z": 89, "Datum": "39.215733"}, {"X": 14, "Y": 44, "Z": 90, "Datum": "26.01547"}, {"X": 14, "Y": 45, "Z": 72, "Datum": "17.584301"}, {"X": 14, "Y": 45, "Z": 73, "Datum": "21.427334"}, {"X": 14, "Y": 45, "Z": 83, "Datum": "28.237686"}, {"X": 14, "Y": 45, "Z": 86, "Datum": "19.658794"}, {"X": 14, "Y": 45, "Z": 87, "Datum": "25.093264"}, {"X": 14, "Y": 45, "Z": 88, "Datum": "33.50237"}, {"X": 14, "Y": 45, "Z": 89, "Datum": "27.109463"}, {"X": 15, "Y": 20, "Z": 55, "Datum": "22.25723"}, {"X": 15, "Y": 20, "Z": 56, "Datum": "17.95877"}, {"X": 15, "Y": 21, "Z": 55, "Datum": "29.13173"}, {"X": 15, "Y": 21, "Z": 56, "Datum": "20.09922"}, {"X": 15, "Y": 22, "Z": 55, "Datum": "24.333948"}, {"X": 15, "Y": 22, "Z": 56, "Datum": "15.045433"}, {"X": 15, "Y": 42, "Z": 72, "Datum": "17.650335"}, {"X": 15, "Y": 42, "Z": 73, "Datum": "15.065706"}, {"X": 15, "Y": 43, "Z": 71, "Datum": "18.002047"}, {"X": 15, "Y": 43, "Z": 72, "Datum": "31.492464"}, {"X": 15, "Y": 43, "Z": 73, "Datum": "25.871357"}, {"X": 15, "Y": 44, "Z": 72, "Datum": "21.875822"}, {"X": 15, "Y": 44, "Z": 73, "Datum": "18.9474"}, {"X": 15, "Y": 45, "Z": 73, "Datum": "18.945423"}, {"X": 15, "Y": 45, "Z": 74, "Datum": "28.423712"}, {"X": 15, "Y": 45, "Z": 75, "Datum": "22.697052"}, {"X": 15, "Y": 45, "Z": 82, "Datum": "17.221312"}, {"X": 15, "Y": 45, "Z": 83, "Datum": "20.174156"}, {"X": 15, "Y": 46, "Z": 73, "Datum": "37.02748"}, {"X": 15, "Y": 46, "Z": 74, "Datum": "47.051407"}, {"X": 15, "Y": 46, "Z": 75, "Datum": "22.551489"}, {"X": 15, "Y": 46, "Z": 82, "Datum": "15.110283"}, {"X": 15, "Y": 47, "Z": 72, "Datum": "28.045607"}, {"X": 15, "Y": 47, "Z": 73, "Datum": "69.79695"}, {"X": 15, "Y": 47, "Z": 74, "Datum": "66.19637"}, {"X": 15, "Y": 47, "Z": 75, "Datum": "21.663218"}, {"X": 15, "Y": 47, "Z": 81, "Datum": "21.419685"}, {"X": 15, "Y": 48, "Z": 72, "Datum": "51.900185"}, {"X": 15, "Y": 48, "Z": 73, "Datum": "90.43252"}, {"X": 15, "Y": 48, "Z": 74, "Datum": "79.368225"}, {"X": 15, "Y": 48, "Z": 75, "Datum": "24.440184"}, {"X": 15, "Y": 48, "Z": 78, "Datum": "16.224213"}, {"X": 15, "Y": 48, "Z": 79, "Datum": "25.971796"}, {"X": 15, "Y": 48, "Z": 80, "Datum": "28.598555"}, {"X": 15, "Y": 48, "Z": 81, "Datum": "16.790733"}, {"X": 15, "Y": 49, "Z": 77, "Datum": "107.35198"}, {"X": 15, "Y": 49, "Z": 78, "Datum": "80.79889"}, {"X": 15, "Y": 49, "Z": 79, "Datum": "46.450024"}, {"X": 15, "Y": 49, "Z": 80, "Datum": "24.485317"}, {"X": 15, "Y": 50, "Z": 77, "Datum": "191.9069"}, {"X": 15, "Y": 50, "Z": 78, "Datum": "105.202156"}, {"X": 15, "Y": 50, "Z": 79, "Datum": "40.738567"}, {"X": 15, "Y": 51, "Z": 78, "Datum": "55.401882"}, {"X": 15, "Y": 51, "Z": 79, "Datum": "34.85226"}, {"X": 16, "Y": 45, "Z": 74, "Datum": "16.953249"}, {"X": 16, "Y": 46, "Z": 73, "Datum": "19.28839"}, {"X": 16, "Y": 46, "Z": 74, "Datum": "23.940403"}, {"X": 16, "Y": 47, "Z": 72, "Datum": "20.8251"}, {"X": 16, "Y": 47, "Z": 73, "Datum": "37.19595"}, {"X": 16, "Y": 47, "Z": 74, "Datum": "33.783375"}, {"X": 16, "Y": 48, "Z": 72, "Datum": "26.855516"}, {"X": 16, "Y": 48, "Z": 73, "Datum": "42.755463"}, {"X": 16, "Y": 48, "Z": 74, "Datum": "34.065933"}, {"X": 16, "Y": 48, "Z": 80, "Datum": "15.497911"}, {"X": 16, "Y": 49, "Z": 72, "Datum": "18.745434"}, {"X": 16, "Y": 49, "Z": 73, "Datum": "37.195885"}, {"X": 16, "Y": 49, "Z": 74, "Datum": "35.049225"}, {"X": 16, "Y": 49, "Z": 75, "Datum": "19.03206"}, {"X": 16, "Y": 49, "Z": 76, "Datum": "22.902687"}, {"X": 16, "Y": 49, "Z": 77, "Datum": "48.676926"}, {"X": 16, "Y": 49, "Z": 78, "Datum": "43.77282"}, {"X": 16, "Y": 49, "Z": 79, "Datum": "25.355051"}, {"X": 16, "Y": 50, "Z": 72, "Datum": "30.59081"}, {"X": 16, "Y": 50, "Z": 73, "Datum": "58.45633"}, {"X": 16, "Y": 50, "Z": 74, "Datum": "67.84326"}, {"X": 16, "Y": 50, "Z": 75, "Datum": "56.728565"}, {"X": 16, "Y": 50, "Z": 76, "Datum": "60.30675"}, {"X": 16, "Y": 50, "Z": 77, "Datum": "86.72425"}, {"X": 16, "Y": 50, "Z": 78, "Datum": "64.94887"}, {"X": 16, "Y": 50, "Z": 79, "Datum": "25.602766"}, {"X": 16, "Y": 51, "Z": 72, "Datum": "36.346737"}, {"X": 16, "Y": 51, "Z": 73, "Datum": "53.876995"}, {"X": 16, "Y": 51, "Z": 74, "Datum": "64.424866"}, {"X": 16, "Y": 51, "Z": 75, "Datum": "65.313095"}, {"X": 16, "Y": 51, "Z": 76, "Datum": "62.22995"}, {"X": 16, "Y": 51, "Z": 77, "Datum": "57.181454"}, {"X": 16, "Y": 51, "Z": 78, "Datum": "42.386932"}, {"X": 16, "Y": 51, "Z": 79, "Datum": "20.525185"}, {"X": 16, "Y": 52, "Z": 72, "Datum": "22.642956"}, {"X": 16, "Y": 52, "Z": 73, "Datum": "24.111704"}, {"X": 16, "Y": 52, "Z": 74, "Datum": "29.702131"}, {"X": 16, "Y": 52, "Z": 75, "Datum": "36.14062"}, {"X": 16, "Y": 52, "Z": 76, "Datum": "30.723074"}, {"X": 16, "Y": 52, "Z": 77, "Datum": "18.905767"}, {"X": 17, "Y": 49, "Z": 73, "Datum": "19.316914"}, {"X": 17, "Y": 49, "Z": 74, "Datum": "17.74289"}, {"X": 17, "Y": 50, "Z": 72, "Datum": "15.047385"}, {"X": 17, "Y": 50, "Z": 73, "Datum": "30.72403"}, {"X": 17, "Y": 50, "Z": 74, "Datum": "34.56571"}, {"X": 17, "Y": 50, "Z": 75, "Datum": "28.966469"}, {"X": 17, "Y": 50, "Z": 76, "Datum": "31.014044"}, {"X": 17, "Y": 50, "Z": 77, "Datum": "31.218828"}, {"X": 17, "Y": 50, "Z": 78, "Datum": "18.287281"}, {"X": 17, "Y": 51, "Z": 72, "Datum": "18.386408"}, {"X": 17, "Y": 51, "Z": 73, "Datum": "29.129496"}, {"X": 17, "Y": 51, "Z": 74, "Datum": "33.517097"}, {"X": 17, "Y": 51, "Z": 75, "Datum": "34.87565"}, {"X": 17, "Y": 51, "Z": 76, "Datum": "33.965534"}, {"X": 17, "Y": 51, "Z": 77, "Datum": "31.333881"}, {"X": 17, "Y": 51, "Z": 78, "Datum": "21.639751"}, {"X": 17, "Y": 52, "Z": 74, "Datum": "16.846207"}, {"X": 17, "Y": 52, "Z": 75, "Datum": "21.632393"}, {"X": 17, "Y": 52, "Z": 76, "Datum": "19.0191"}], "smoke": []}